odoo/addons/shopinvader_product_sale_packaging/README.rst
odoo/addons/shopinvader_product_sale_packaging/__init__.py
odoo/addons/shopinvader_product_sale_packaging/__manifest__.py
odoo/addons/shopinvader_product_sale_packaging/i18n/shopinvader_product_sale_packaging.pot
odoo/addons/shopinvader_product_sale_packaging/models/__init__.py
odoo/addons/shopinvader_product_sale_packaging/models/product_packaging.py
odoo/addons/shopinvader_product_sale_packaging/models/product_packaging_level.py
odoo/addons/shopinvader_product_sale_packaging/readme/CONTRIBUTORS.rst
odoo/addons/shopinvader_product_sale_packaging/readme/CREDITS.rst
odoo/addons/shopinvader_product_sale_packaging/readme/DESCRIPTION.rst
odoo/addons/shopinvader_product_sale_packaging/schemas/__init__.py
odoo/addons/shopinvader_product_sale_packaging/schemas/product.py
odoo/addons/shopinvader_product_sale_packaging/schemas/product_packaging.py
odoo/addons/shopinvader_product_sale_packaging/static/description/index.html
odoo/addons/shopinvader_product_sale_packaging/tests/__init__.py
odoo/addons/shopinvader_product_sale_packaging/tests/common.py
odoo/addons/shopinvader_product_sale_packaging/tests/test_product_data.py
odoo/addons/shopinvader_product_sale_packaging/tests/test_product_packaging_schema.py
odoo/addons/shopinvader_product_sale_packaging/views/product_packaging.xml
odoo/addons/shopinvader_product_sale_packaging/views/product_packaging_level.xml
odoo_addon_shopinvader_product_sale_packaging-16.0.1.0.2.dist-info/METADATA
odoo_addon_shopinvader_product_sale_packaging-16.0.1.0.2.dist-info/WHEEL
odoo_addon_shopinvader_product_sale_packaging-16.0.1.0.2.dist-info/top_level.txt
odoo_addon_shopinvader_product_sale_packaging-16.0.1.0.2.dist-info/RECORD
